wjszzk/src/__init__.py
wjszzk/src/day11_afford_pipeline.py
wjszzk/src/day11_behavior_flags_pipeline.py
wjszzk/src/day11_credit_behavior_pipeline.py
wjszzk/src/day11_expense_structure_pipeline.py
wjszzk/src/day11_geo_cohort_pipeline.py
wjszzk/src/day11_income_stab_pipeline.py
wjszzk/src/day11_liquidity_shock_pipeline.py
wjszzk/src/day11_team_features_pipeline.py
wjszzk/src/day3_features.py
wjszzk/src/day4_add_pipeline.py
wjszzk/src/day4_mul_pipeline.py
wjszzk/src/day7_bins_pipeline.py
wjszzk/src/day7_rec_pipeline.py
wjszzk/src/day7_time_pipeline.py
wjszzk/src/day8_cluster_pipeline.py
wjszzk/src/day8_cross_pipeline.py
wjszzk/src/day8_lag_pipeline.py
wjszzk/src/day8_poly_pipeline.py
wjszzk/src/day8_ratio_pipeline.py
wjszzk/src/readme.py
wjszzk/src/requirements.py
wjszzk/src/run_all.py
wjszzk/src/run_features.py
wjszzk/src/test.py
wjszzk/src/train.py
wjszzk-0.1.0.dist-info/METADATA
wjszzk-0.1.0.dist-info/WHEEL
wjszzk-0.1.0.dist-info/top_level.txt
wjszzk-0.1.0.dist-info/RECORD
